safe_filefield/__init__.py
safe_filefield/clamav.py
safe_filefield/default_settings.py
safe_filefield/forms.py
safe_filefield/models.py
safe_filefield/utils.py
safe_filefield/validators.py
django_safe_filefield-1.0.0.dist-info/LICENSE
django_safe_filefield-1.0.0.dist-info/METADATA
django_safe_filefield-1.0.0.dist-info/WHEEL
django_safe_filefield-1.0.0.dist-info/top_level.txt
django_safe_filefield-1.0.0.dist-info/RECORD
