Metadata-Version: 2.1
Name: django-safe-filefield
Version: 1.0.0
Summary: Secure file field, which allows you to restrict uploaded file extensions.
Home-page: https://github.com/mixkorshun/django-safe-filefield
Author: Vladislav Bakin
Author-email: mixkorshun@gmail.com
Maintainer: Vladislav Bakin
Maintainer-email: mixkorshun@gmail.com
License: MIT
Keywords: django,filefield,model-field,form-field
Classifier: Development Status :: 5 - Production/Stable
Classifier: Intended Audience :: Developers
Classifier: Topic :: Security
Classifier: License :: OSI Approved :: MIT License
Classifier: Programming Language :: Python
Classifier: Programming Language :: Python :: 3
Classifier: Programming Language :: Python :: 3.7
Classifier: Programming Language :: Python :: 3.8
Classifier: Programming Language :: Python :: 3.9
Classifier: Programming Language :: Python :: 3.10
Classifier: Programming Language :: Python :: 3.11
Classifier: Framework :: Django
Classifier: Framework :: Django :: 1.11
Classifier: Framework :: Django :: 1.11
Classifier: Framework :: Django :: 2
Classifier: Framework :: Django :: 2.2
Classifier: Framework :: Django :: 3
Classifier: Framework :: Django :: 3.2
Classifier: Framework :: Django :: 4
Classifier: Framework :: Django :: 4.2
License-File: LICENSE
Requires-Dist: django
Requires-Dist: python-magic
Requires-Dist: clamd
